multiloginlocal/__init__.py
multiloginlocal/api_client.py
multiloginlocal/configuration.py
multiloginlocal/rest.py
multiloginlocal/api/__init__.py
multiloginlocal/api/misc_api.py
multiloginlocal/models/__init__.py
multiloginlocal/models/clone_ok_resonse.py
multiloginlocal/models/cookie_json_example.py
multiloginlocal/models/cookie_netscape_example.py
multiloginlocal/models/main_error_response.py
multiloginlocal/models/main_ok_response.py
multiloginlocal/models/profile_active_error_response.py
multiloginlocal/models/profile_active_ok_response.py
multilogin_local_api-1.0.4.dist-info/METADATA
multilogin_local_api-1.0.4.dist-info/WHEEL
multilogin_local_api-1.0.4.dist-info/top_level.txt
multilogin_local_api-1.0.4.dist-info/RECORD
