Metadata-Version: 2.1
Name: multilogin-local-api
Version: 1.0.4
Summary: Multilogin Local REST API
Home-page: https://github.com/lusi1990/multilogin_local_api
Author: Master Lu
Author-email: lusi2114@gmail.com
License: UNKNOWN
Keywords: Swagger,Multilogin Local REST API
Platform: UNKNOWN
Requires-Dist: certifi (>=2017.4.17)
Requires-Dist: python-dateutil (>=2.1)
Requires-Dist: six (>=1.10)
Requires-Dist: urllib3 (>=1.23)
